CONTRIBUTING.md
MANIFEST.in
README.rst
setup.py
docs/HISTORY.txt
docs/LICENSE.GPL
docs/LICENSE.txt
eea/__init__.py
eea.dexterity.themes.egg-info/PKG-INFO
eea.dexterity.themes.egg-info/SOURCES.txt
eea.dexterity.themes.egg-info/dependency_links.txt
eea.dexterity.themes.egg-info/entry_points.txt
eea.dexterity.themes.egg-info/namespace_packages.txt
eea.dexterity.themes.egg-info/not-zip-safe
eea.dexterity.themes.egg-info/requires.txt
eea.dexterity.themes.egg-info/top_level.txt
eea/dexterity/__init__.py
eea/dexterity/themes/README.txt
eea/dexterity/themes/__init__.py
eea/dexterity/themes/configure.zcml
eea/dexterity/themes/interfaces.py
eea/dexterity/themes/profiles.zcml
eea/dexterity/themes/setuphandlers.py
eea/dexterity/themes/version.txt
eea/dexterity/themes/browser/__init__.py
eea/dexterity/themes/browser/configure.zcml
eea/dexterity/themes/locales/__init__.py
eea/dexterity/themes/locales/eea.pot
eea/dexterity/themes/locales/plone-manual.pot
eea/dexterity/themes/locales/update.sh
eea/dexterity/themes/locales/bg/LC_MESSAGES/eea.po
eea/dexterity/themes/locales/bg/LC_MESSAGES/plone.po
eea/dexterity/themes/locales/cs/LC_MESSAGES/eea.po
eea/dexterity/themes/locales/cs/LC_MESSAGES/plone.po
eea/dexterity/themes/locales/da/LC_MESSAGES/eea.po
eea/dexterity/themes/locales/da/LC_MESSAGES/plone.po
eea/dexterity/themes/locales/de/LC_MESSAGES/eea.po
eea/dexterity/themes/locales/de/LC_MESSAGES/plone.po
eea/dexterity/themes/locales/el/LC_MESSAGES/eea.po
eea/dexterity/themes/locales/el/LC_MESSAGES/plone.po
eea/dexterity/themes/locales/en/LC_MESSAGES/eea.po
eea/dexterity/themes/locales/en/LC_MESSAGES/plone.po
eea/dexterity/themes/locales/es/LC_MESSAGES/eea.po
eea/dexterity/themes/locales/es/LC_MESSAGES/plone.po
eea/dexterity/themes/locales/et/LC_MESSAGES/eea.po
eea/dexterity/themes/locales/et/LC_MESSAGES/plone.po
eea/dexterity/themes/locales/eu/LC_MESSAGES/eea.po
eea/dexterity/themes/locales/eu/LC_MESSAGES/plone.po
eea/dexterity/themes/locales/fi/LC_MESSAGES/eea.po
eea/dexterity/themes/locales/fi/LC_MESSAGES/plone.po
eea/dexterity/themes/locales/fr/LC_MESSAGES/eea.po
eea/dexterity/themes/locales/fr/LC_MESSAGES/plone.po
eea/dexterity/themes/locales/hr/LC_MESSAGES/eea.po
eea/dexterity/themes/locales/hr/LC_MESSAGES/plone.po
eea/dexterity/themes/locales/hu/LC_MESSAGES/eea.po
eea/dexterity/themes/locales/hu/LC_MESSAGES/plone.po
